owoify/__init__.py
owoify/constants.py
owoify/owo.py
owoify-0.3.1.dist-info/LICENSE
owoify-0.3.1.dist-info/WHEEL
owoify-0.3.1.dist-info/METADATA
owoify-0.3.1.dist-info/RECORD
