Metadata-Version: 2.1
Name: owoify
Version: 0.3.1
Summary: Cutting edge technologies to owoify your texts
Author: crinny
Requires-Python: >=3.6,<4.0
Classifier: Programming Language :: Python :: 3
Classifier: Programming Language :: Python :: 3.6
Classifier: Programming Language :: Python :: 3.7
Classifier: Programming Language :: Python :: 3.8
